topen.py
topen-0.2.0.dist-info/licenses/LICENSE
topen-0.2.0.dist-info/METADATA
topen-0.2.0.dist-info/WHEEL
topen-0.2.0.dist-info/entry_points.txt
topen-0.2.0.dist-info/top_level.txt
topen-0.2.0.dist-info/RECORD
