Metadata-Version: 2.4
Name: topen
Version: 0.2.0
Summary: simple taskwarrior note management
Project-URL: Documentation, https://marty-oehme.github.io/topen
Project-URL: Repository, https://github.com/marty-oehme/topen
Project-URL: Changelog, https://github.com/marty-oehme/topen/blob/main/CHANGELOG.md
Requires-Python: >=3.13
License-File: LICENSE
Requires-Dist: tasklib>=2.5.1
Dynamic: license-file
